package_ScoreMP/MPscore.py
package_ScoreMP/__init__.py
scoreMP_pkg_USER_NAME-0.0.1.dist-info/LICENSE
scoreMP_pkg_USER_NAME-0.0.1.dist-info/METADATA
scoreMP_pkg_USER_NAME-0.0.1.dist-info/WHEEL
scoreMP_pkg_USER_NAME-0.0.1.dist-info/top_level.txt
scoreMP_pkg_USER_NAME-0.0.1.dist-info/RECORD
