Metadata-Version: 2.1
Name: scoreMP-pkg-USER-NAME
Version: 0.0.1
Summary: A smallexamplepackage
Home-page: https://github.com/pypa/sampleproject
Author: Example Author
Author-email: author@example.com
Project-URL: Bug Tracker, https://github.com/pypa/sampleproject/issues
License-File: LICENSE
